README.md
setup.py
sicomor_especificaciones/__init__.py
sicomor_especificaciones/hardware_inv.py
sicomor_especificaciones/inventario.py
sicomor_especificaciones/sistop_inv.py
sicomor_especificaciones/software_inv.py
sicomor_especificaciones.egg-info/PKG-INFO
sicomor_especificaciones.egg-info/SOURCES.txt
sicomor_especificaciones.egg-info/dependency_links.txt
sicomor_especificaciones.egg-info/top_level.txt